gocept.cache-6.0-py3.12-nspkg.pth
gocept/cache/README.rst
gocept/cache/__init__.py
gocept/cache/method.py
gocept/cache/property.py
gocept/cache/tests/__init__.py
gocept/cache/tests/test_method.py
gocept/cache/tests/test_property.py
gocept_cache-6.0.dist-info/LICENSE.txt
gocept_cache-6.0.dist-info/METADATA
gocept_cache-6.0.dist-info/WHEEL
gocept_cache-6.0.dist-info/namespace_packages.txt
gocept_cache-6.0.dist-info/top_level.txt
gocept_cache-6.0.dist-info/RECORD
